pystiyle/__init__.py
pystiyle-2.8.dist-info/METADATA
pystiyle-2.8.dist-info/WHEEL
pystiyle-2.8.dist-info/top_level.txt
pystiyle-2.8.dist-info/RECORD
